insightfinderai/__init__.py
insightfinderai/client.py
insightfinderai/config.py
insightfinderai/conversation.py
insightfinderai/model/__init__.py
insightfinderai/model/batch_chat_result.py
insightfinderai/model/batch_comparison_result.py
insightfinderai/model/batch_evaluation_result.py
insightfinderai/model/chat_response.py
insightfinderai/model/evaluation_result.py
insightfinderai/model/session_list.py
insightfinderai/model/session_token_usage.py
insightfinderai/model/usage_stats.py
insightfinderai-2.4.16.dist-info/licenses/LICENSE
tests/__init__.py
tests/simple_batch_eval_test.py
tests/simple_batch_test.py
tests/simple_chat_test.py
tests/simple_context_test.py
tests/simple_evaluation_test.py
tests/simple_history_test.py
tests/simple_safety_test.py
tests/simple_save_load_test.py
tests/simple_session_test.py
insightfinderai-2.4.16.dist-info/METADATA
insightfinderai-2.4.16.dist-info/WHEEL
insightfinderai-2.4.16.dist-info/top_level.txt
insightfinderai-2.4.16.dist-info/RECORD
