Metadata-Version: 2.4
Name: insightfinderai
Version: 2.4.16
Summary: A Python SDK for interfacing with the InsightFinder API.
Author-email: InsightFinderAI <support@insightfinder.com>
License-Expression: Apache-2.0
Project-URL: Homepage, https://insightfinder.com/
Project-URL: Repository, https://github.com/insightfinder/ifai-sdk
Keywords: insightfinderai,sdk,api
Classifier: Development Status :: 3 - Alpha
Classifier: Intended Audience :: Developers
Classifier: Programming Language :: Python :: 3
Classifier: Programming Language :: Python :: 3.7
Classifier: Programming Language :: Python :: 3.8
Classifier: Programming Language :: Python :: 3.9
Classifier: Programming Language :: Python :: 3.10
Classifier: Programming Language :: Python :: 3.11
Classifier: Programming Language :: Python :: 3.12
Classifier: Operating System :: OS Independent
Requires-Python: >=3.7
License-File: LICENSE
Requires-Dist: requests
Provides-Extra: test
Requires-Dist: pytest; extra == "test"
Requires-Dist: coverage; extra == "test"
Provides-Extra: dev
Requires-Dist: pre-commit; extra == "dev"
Requires-Dist: black; extra == "dev"
Requires-Dist: mypy; extra == "dev"
Dynamic: license-file
